LICENSE
MANIFEST.in
README.rst
setup.py
wal_e/VERSION
wal_e/__init__.py
wal_e/channel.py
wal_e/cmd.py
wal_e/copyfileobj.py
wal_e/exception.py
wal_e/files.py
wal_e/log_help.py
wal_e/pipebuf.py
wal_e/pipeline.py
wal_e/piper.py
wal_e/retries.py
wal_e/tar_partition.py
wal_e.egg-info/PKG-INFO
wal_e.egg-info/SOURCES.txt
wal_e.egg-info/dependency_links.txt
wal_e.egg-info/entry_points.txt
wal_e.egg-info/requires.txt
wal_e.egg-info/top_level.txt
wal_e/blobstore/__init__.py
wal_e/blobstore/file/__init__.py
wal_e/blobstore/file/calling_format.py
wal_e/blobstore/file/file_credentials.py
wal_e/blobstore/file/file_util.py
wal_e/blobstore/gs/__init__.py
wal_e/blobstore/gs/calling_format.py
wal_e/blobstore/gs/credentials.py
wal_e/blobstore/gs/utils.py
wal_e/blobstore/s3/__init__.py
wal_e/blobstore/s3/calling_format.py
wal_e/blobstore/s3/s3_credentials.py
wal_e/blobstore/s3/s3_util.py
wal_e/blobstore/swift/__init__.py
wal_e/blobstore/swift/calling_format.py
wal_e/blobstore/swift/credentials.py
wal_e/blobstore/swift/utils.py
wal_e/blobstore/wabs/__init__.py
wal_e/blobstore/wabs/calling_format.py
wal_e/blobstore/wabs/wabs_credentials.py
wal_e/blobstore/wabs/wabs_util.py
wal_e/operator/__init__.py
wal_e/operator/backup.py
wal_e/operator/file_operator.py
wal_e/operator/gs_operator.py
wal_e/operator/s3_operator.py
wal_e/operator/swift_operator.py
wal_e/operator/wabs_operator.py
wal_e/pep3143daemon/LICENSE.txt
wal_e/pep3143daemon/__init__.py
wal_e/pep3143daemon/daemon.py
wal_e/pep3143daemon/pidfile.py
wal_e/storage/__init__.py
wal_e/storage/base.py
wal_e/storage/file_storage.py
wal_e/storage/gs_storage.py
wal_e/storage/s3_storage.py
wal_e/storage/swift_storage.py
wal_e/storage/wabs_storage.py
wal_e/worker/__init__.py
wal_e/worker/base.py
wal_e/worker/prefetch.py
wal_e/worker/upload.py
wal_e/worker/upload_pool.py
wal_e/worker/worker_util.py
wal_e/worker/file/__init__.py
wal_e/worker/file/file_deleter.py
wal_e/worker/file/file_worker.py
wal_e/worker/gs/__init__.py
wal_e/worker/gs/gs_deleter.py
wal_e/worker/gs/gs_worker.py
wal_e/worker/pg/__init__.py
wal_e/worker/pg/pg_controldata_worker.py
wal_e/worker/pg/psql_worker.py
wal_e/worker/pg/wal_transfer.py
