Metadata-Version: 2.1
Name: wal-e
Version: 1.1.1
Summary: Continuous Archiving for Postgres
Home-page: https://github.com/wal-e/wal-e
Author: The WAL-E Contributors
Author-email: wal-e@googlegroups.com
Maintainer: Daniel Farina
Maintainer-email: daniel@fdr.io
License: BSD
Keywords: postgres postgresql database backup archive archiving s3 aws openstack swift wabs azure google gce gcs wal shipping
Platform: any
Classifier: Topic :: Database
Classifier: Topic :: System :: Archiving
Classifier: Topic :: System :: Recovery Tools
Classifier: Programming Language :: Python :: 3.4
Classifier: Programming Language :: Python :: 3.5
Provides-Extra: aws
Provides-Extra: azure
Provides-Extra: google
Provides-Extra: swift
